temeco/interface.py
temeco/temeco.py
temeco-0.1.3.dist-info/LICENSE
temeco-0.1.3.dist-info/WHEEL
temeco-0.1.3.dist-info/METADATA
temeco-0.1.3.dist-info/RECORD
