Metadata-Version: 2.1
Name: temeco
Version: 0.1.3
Summary: A small package handling telegram message copying preserving text entities
Home-page: https://github.com/monomonedula/temeco
License: MIT
Keywords: telegram,encoding,telegram-bot-api,utility
Author: monomonedula
Author-email: valh@tuta.io
Requires-Python: >=3.6,<4.0
Classifier: License :: OSI Approved :: MIT License
Classifier: Programming Language :: Python :: 3
Classifier: Programming Language :: Python :: 3.6
Classifier: Programming Language :: Python :: 3.7
Classifier: Programming Language :: Python :: 3.8
Project-URL: Repository, https://github.com/monomonedula/temeco
